fastoai/__init__.py
fastoai/__main__.py
fastoai/_client.py
fastoai/cli.py
fastoai/dependencies.py
fastoai/pagination.py
fastoai/py.typed
fastoai/settings.py
fastoai/models/__init__.py
fastoai/models/_codegen.py
fastoai/models/_metadata.py
fastoai/models/_types.py
fastoai/models/_utils.py
fastoai/models/key.py
fastoai/models/organization.py
fastoai/models/organization_user.py
fastoai/models/project.py
fastoai/models/project_user.py
fastoai/models/service_account.py
fastoai/models/user.py
fastoai/models/generated/assistant.py
fastoai/models/generated/file_object.py
fastoai/models/generated/message.py
fastoai/models/generated/run.py
fastoai/models/generated/run_step.py
fastoai/models/generated/thread.py
fastoai/routers/__init__.py
fastoai/routers/_client.py
fastoai/routers/_types.py
fastoai/routers/files.py
fastoai/routers/models.py
fastoai/routers/beta/__init__.py
fastoai/routers/beta/assistants.py
fastoai/routers/beta/messages.py
fastoai/routers/beta/run_steps.py
fastoai/routers/beta/runs.py
fastoai/routers/beta/threads.py
fastoai-1.0.3.dist-info/METADATA
fastoai-1.0.3.dist-info/WHEEL
fastoai-1.0.3.dist-info/entry_points.txt
fastoai-1.0.3.dist-info/RECORD
