Metadata-Version: 2.4
Name: fastoai
Version: 1.0.3
Summary: Start an API server as OpenAI's
Author-email: Tang Ziya <tcztzy@gmail.Com>
Requires-Python: >=3.13
Requires-Dist: aiosqlite>=0.21.0
Requires-Dist: anthropic>=0.45.2
Requires-Dist: asyncpg>=0.30.0
Requires-Dist: asyncstdlib>=3.13.0
Requires-Dist: bcrypt>=4.2.1
Requires-Dist: fastapi[standard]>=0.115.8
Requires-Dist: fsspec[full]>=2025.2.0
Requires-Dist: loguru>=0.7.3
Requires-Dist: openai>=1.61.1
Requires-Dist: pydantic-settings>=2.7.1
Requires-Dist: pydantic[email]>=2.10.6
Requires-Dist: ruff>=0.9.5
Requires-Dist: sqlalchemy[asyncio]>=2.0.38
Requires-Dist: sqlmodel>=0.0.22
Requires-Dist: tenacity>=9.0.0
Requires-Dist: typer>=0.15.1
Requires-Dist: uvicorn[standard]>=0.34.0
Requires-Dist: valkey[libvalkey]>=6.0.2
